django_test_urls/__init__.py
django_test_urls/exceptions.py
django_test_urls/resolves_to.py
django_test_urls-0.3.0.dist-info/LICENSE
django_test_urls-0.3.0.dist-info/METADATA
django_test_urls-0.3.0.dist-info/WHEEL
django_test_urls-0.3.0.dist-info/top_level.txt
django_test_urls-0.3.0.dist-info/RECORD
